evernotezimport/__init__.py
evernotezimport/main.py
evernotezimport/templates/zim.template
evernotezimport-1.0.0.data/data/evernotezimport/templates/zim.template
evernotezimport-1.0.0.dist-info/AUTHORS
evernotezimport-1.0.0.dist-info/LICENSE
evernotezimport-1.0.0.dist-info/METADATA
evernotezimport-1.0.0.dist-info/WHEEL
evernotezimport-1.0.0.dist-info/entry_points.txt
evernotezimport-1.0.0.dist-info/pbr.json
evernotezimport-1.0.0.dist-info/top_level.txt
evernotezimport-1.0.0.dist-info/RECORD
