Metadata-Version: 2.1
Name: evernotezimport
Version: 1.0.0
Summary: Import Evernote export into Zim notes
Home-page: https://git.kotur.org/kotnik/evernotezimport
Author: Nikola Kotur
Author-email: kotnick@gmail.com
License: MIT
Platform: UNKNOWN
Requires-Dist: pbr
Requires-Dist: beautifulsoup4
Requires-Dist: jinja2
Requires-Dist: logzero
Requires-Dist: python-dateutil
